setup.cfg
setup.py
pysentech/__init__.py
pysentech/camera.py
pysentech/error.py
pysentech/frame.py
pysentech/sentechdll.py
pysentech/system.py
pysentech.egg-info/PKG-INFO
pysentech.egg-info/SOURCES.txt
pysentech.egg-info/dependency_links.txt
pysentech.egg-info/not-zip-safe
pysentech.egg-info/top_level.txt